[
    {
        "name": "Производство",
        "filters": [
            "АиР",
            "Булат Сергея Баранова",
            "Булат Умерова",
            "ЗЗОСС",
            "ЗИК",
            "ЗЛАТКО",
            "ЗлатПрофит",
            "ЗОК"
        ]
    },
    {
        "name": "Сталь",
        "filters": [
            "100Х13М",
            "110Х18М-ШД",
            "40Х10С2М (ЭИ-107)",
            "50Х14МФ",
            "95Х18",
            "AUS-8",
            "ELMAX",
            "RWL-34",
            "Дамаск",
            "К340",
            "Литой булат",
            "Литой булат",
            "Литой булат",
            "М390"
        ]
    },
    {
        "name": "Рукоять",
        "filters": [
            "Mercorne",
            "Березовый кап",
            "Бубинго",
            "Граб",
            "Дуб",
            "Кап",
            "Комбинированная",
            "Каштан",
            "Квартопрен",
            "Кожа-Металл",
            "Комбинированная"
        ]
    },
    {
        "name": "Гарда и тыльник",
        "filters": [
            "Алюминий",
            "Латунь",
            "Литой Барс",
            "Литой Барс",
            "Литой Пума",
            "Литой Пума",
            "Литье",
            "Металлический",
            "Нержавеющая сталь",
            "Текстолит",
            "Комбинированная"
        ]
    }

]

